fantacalciosimulator/__init__.py
fantacalciosimulator/lib.py
fantacalciosimulator/loader.py
fantacalciosimulator/player.py
fantacalciosimulator/playerstats.py
fantacalciosimulator/probabilisticseason.py
fantacalciosimulator/role.py
fantacalciosimulator/team.py
fantacalciosimulator-0.1.3.dist-info/licenses/LICENSE
fantacalciosimulator-0.1.3.dist-info/METADATA
fantacalciosimulator-0.1.3.dist-info/WHEEL
fantacalciosimulator-0.1.3.dist-info/top_level.txt
fantacalciosimulator-0.1.3.dist-info/RECORD
