Metadata-Version: 2.4
Name: fantacalciosimulator
Version: 0.1.3
Summary: A python tool to simulate an entire Fantacalcio season
Author-email: Riccardo Samaritan <riccardo.samaritan@gmail.com>
License: MIT License
Project-URL: Repository, https://github.com/RiccardoSamaritan/FantacalcioSimulator
Keywords: fantacalcio,simulation,football,fantasy football
Classifier: Programming Language :: Python :: 3.8
Classifier: Programming Language :: Python :: 3.9
Classifier: Programming Language :: Python :: 3.10
Classifier: Programming Language :: Python :: 3.11
Classifier: Programming Language :: Python :: 3.12
Classifier: Programming Language :: Python :: 3.13
Classifier: License :: OSI Approved :: MIT License
Classifier: Operating System :: OS Independent
Requires-Python: >=3.8
License-File: LICENSE
Requires-Dist: pandas>=2.0.0
Requires-Dist: send2trash>=1.8.0
Dynamic: license-file
